TestPackage/TestModule.py
TestPackage/__init__.py
PythonTutorial-1.0.dist-info/LICENCE
PythonTutorial-1.0.dist-info/METADATA
PythonTutorial-1.0.dist-info/WHEEL
PythonTutorial-1.0.dist-info/top_level.txt
PythonTutorial-1.0.dist-info/RECORD
